pyawg/__init__.py
pyawg/awg_control.py
pyawg/base.py
pyawg/enums.py
pyawg/exceptions.py
pyawg/rigol.py
pyawg/siglent.py
pyawg/utils.py
pyawg-0.4.0.0.dist-info/LICENSE
pyawg-0.4.0.0.dist-info/METADATA
pyawg-0.4.0.0.dist-info/WHEEL
pyawg-0.4.0.0.dist-info/RECORD
