Metadata-Version: 2.1
Name: pyawg
Version: 0.4.0.0
Summary: Simple python library to control Arbitrary Waveform Generators from various manufacturers.
Home-page: https://github.com/abhishekbawkar/pyawg
Author: Abhishek Bawkar
Author-email: abhishekbawkar@gmail.com
Requires-Python: >=3.8,<4.0
Classifier: Programming Language :: Python :: 3
Classifier: Programming Language :: Python :: 3.8
Classifier: Programming Language :: Python :: 3.9
Classifier: Programming Language :: Python :: 3.10
Classifier: Programming Language :: Python :: 3.11
Classifier: Programming Language :: Python :: 3.12
Classifier: Programming Language :: Python :: 3.13
Requires-Dist: python-vxi11 (>=0.9,<0.10)
Project-URL: Documentation, https://github.com/abhishekbawkar/pyawg/blob/master/README.md
Project-URL: Repository, https://github.com/abhishekbawkar/pyawg
